cltl/__init__.py
cltl/naoqi/__init__.py
cltl/naoqi/__main__.py
cltl/naoqi/app.py
cltl/naoqi/app_tablet.py
cltl/naoqi/audio_source.py
cltl/naoqi/behaviour.py
cltl/naoqi/image_source.py
cltl/naoqi/server.py
cltl/naoqi/tts_output.py
cltl/naoqi/api/__init__.py
cltl/naoqi/api/camera.py
cltl/naoqi/api/microphone.py
cltl/naoqi/spi/__init__.py
cltl/naoqi/spi/audio.py
cltl/naoqi/spi/behaviour.py
cltl/naoqi/spi/image.py
cltl/naoqi/spi/text.py
cltl.backend_naoqi-0.0.dev12.data/data/VERSION/VERSION
cltl.backend_naoqi-0.0.dev12.dist-info/LICENSE
cltl.backend_naoqi-0.0.dev12.dist-info/METADATA
cltl.backend_naoqi-0.0.dev12.dist-info/WHEEL
cltl.backend_naoqi-0.0.dev12.dist-info/entry_points.txt
cltl.backend_naoqi-0.0.dev12.dist-info/top_level.txt
cltl.backend_naoqi-0.0.dev12.dist-info/RECORD
