Metadata-Version: 2.1
Name: cltl.backend-naoqi
Version: 0.0.dev12
Summary: Backend for Pepper robot
Home-page: https://github.com/leolani/cltl-backend-naoqi
Author: CLTL
Author-email: t.baier@vu.nl
License: MIT License
Requires-Python: >=2.7.0,<=3.0.0
License-File: LICENSE
Requires-Dist: numpy
Requires-Dist: flask
Requires-Dist: click
Requires-Dist: enum34
Requires-Dist: jinja2
Requires-Dist: MarkupSafe
Requires-Dist: itsdangerous
